{"OutputFileHashSum":"0E513A9F34D9DF0254A68F74B77AA291464EB0DDDBE07EFD05C7D65E16491CA1","Converted":true,"OutputModifyDate":"2024-12-11T11:46:12.6506534Z","Metadatas":[],"MetadataTypes":[{"CategoryName":"VuGen.Replay","MetadataTypeName":"HP.LR.Vugen.Warning","Id":1},{"CategoryName":"VuGen.Replay","MetadataTypeName":"HP.LR.Vugen.Iteration","Id":2},{"CategoryName":"VuGen.Replay","MetadataTypeName":"HP.LR.Vugen.NotifyTransaction","Id":3},{"CategoryName":"VuGen.Replay","MetadataTypeName":"HP.LR.Vugen.NotifySavingParameter","Id":4},{"CategoryName":"VuGen.Replay","MetadataTypeName":"HP.LR.Vugen.NotifyAny","Id":5}]}