{"OutputFileHashSum":"CF42834A8799F18F3281F4138C7D815F42397D11FB244C97DEF9AC0A03DA1E10","Converted":true,"OutputModifyDate":"2024-12-05T19:56:15.6740919Z","Metadatas":[{"CategoryName":"VuGen.Replay","Offset":3034,"Length":23,"TypeId":1},{"CategoryName":"VuGen.Replay","Offset":3160,"Length":63,"TypeId":2},{"CategoryName":"VuGen.Replay","Offset":3223,"Length":62,"TypeId":2},{"CategoryName":"VuGen.Replay","Offset":30499,"Length":101,"TypeId":6},{"CategoryName":"VuGen.Replay","Offset":32867,"Length":120,"TypeId":2},{"CategoryName":"VuGen.Replay","Offset":33051,"Length":137,"TypeId":3},{"CategoryName":"VuGen.Replay","Offset":33188,"Length":100,"TypeId":3},{"CategoryName":"VuGen.Replay","Offset":33381,"Length":52,"TypeId":2},{"CategoryName":"VuGen.Replay","Offset":33491,"Length":86,"TypeId":7},{"CategoryName":"VuGen.Replay","Offset":33732,"Length":110,"TypeId":3},{"CategoryName":"VuGen.Replay","Offset":34469,"Length":120,"TypeId":7},{"CategoryName":"VuGen.Replay","Offset":34589,"Length":86,"TypeId":7},{"CategoryName":"VuGen.Replay","Offset":34675,"Length":79,"TypeId":7},{"CategoryName":"VuGen.Replay","Offset":57718,"Length":110,"TypeId":2},{"CategoryName":"VuGen.Replay","Offset":57828,"Length":66,"TypeId":2},{"CategoryName":"VuGen.Replay","Offset":81694,"Length":68,"TypeId":6},{"CategoryName":"VuGen.Replay","Offset":81762,"Length":68,"TypeId":6},{"CategoryName":"VuGen.Replay","Offset":85141,"Length":125,"TypeId":2},{"CategoryName":"VuGen.Replay","Offset":85429,"Length":122,"TypeId":5},{"CategoryName":"VuGen.Replay","Offset":85551,"Length":79,"TypeId":7},{"CategoryName":"VuGen.Replay","Offset":85630,"Length":122,"TypeId":5},{"CategoryName":"VuGen.Replay","Offset":85752,"Length":82,"TypeId":7},{"CategoryName":"VuGen.Replay","Offset":85834,"Length":64,"TypeId":6},{"CategoryName":"VuGen.Replay","Offset":85898,"Length":67,"TypeId":6},{"CategoryName":"VuGen.Replay","Offset":86058,"Length":60,"TypeId":2},{"CategoryName":"VuGen.Replay","Offset":86177,"Length":83,"TypeId":7},{"CategoryName":"VuGen.Replay","Offset":86260,"Length":86,"TypeId":7},{"CategoryName":"VuGen.Replay","Offset":86346,"Length":87,"TypeId":7},{"CategoryName":"VuGen.Replay","Offset":86511,"Length":81,"TypeId":7},{"CategoryName":"VuGen.Replay","Offset":86592,"Length":63,"TypeId":6},{"CategoryName":"VuGen.Replay","Offset":87537,"Length":83,"TypeId":7},{"CategoryName":"VuGen.Replay","Offset":87620,"Length":87,"TypeId":7},{"CategoryName":"VuGen.Replay","Offset":87707,"Length":86,"TypeId":7},{"CategoryName":"VuGen.Replay","Offset":87793,"Length":87,"TypeId":7},{"CategoryName":"VuGen.Replay","Offset":87880,"Length":82,"TypeId":7},{"CategoryName":"VuGen.Replay","Offset":87962,"Length":90,"TypeId":7},{"CategoryName":"VuGen.Replay","Offset":88052,"Length":83,"TypeId":7},{"CategoryName":"VuGen.Replay","Offset":94989,"Length":76,"TypeId":6},{"CategoryName":"VuGen.Replay","Offset":95065,"Length":76,"TypeId":6},{"CategoryName":"VuGen.Replay","Offset":95141,"Length":76,"TypeId":6},{"CategoryName":"VuGen.Replay","Offset":95217,"Length":76,"TypeId":6},{"CategoryName":"VuGen.Replay","Offset":95293,"Length":63,"TypeId":6},{"CategoryName":"VuGen.Replay","Offset":95678,"Length":118,"TypeId":2},{"CategoryName":"VuGen.Replay","Offset":95796,"Length":82,"TypeId":7},{"CategoryName":"VuGen.Replay","Offset":95878,"Length":95,"TypeId":7},{"CategoryName":"VuGen.Replay","Offset":96024,"Length":78,"TypeId":6},{"CategoryName":"VuGen.Replay","Offset":96102,"Length":76,"TypeId":2},{"CategoryName":"VuGen.Replay","Offset":96261,"Length":97,"TypeId":7},{"CategoryName":"VuGen.Replay","Offset":103339,"Length":134,"TypeId":2},{"CategoryName":"VuGen.Replay","Offset":103473,"Length":60,"TypeId":2},{"CategoryName":"VuGen.Replay","Offset":103616,"Length":97,"TypeId":7},{"CategoryName":"VuGen.Replay","Offset":114428,"Length":118,"TypeId":2},{"CategoryName":"VuGen.Replay","Offset":114546,"Length":122,"TypeId":2},{"CategoryName":"VuGen.Replay","Offset":114691,"Length":21,"TypeId":1}],"MetadataTypes":[{"CategoryName":"VuGen.Replay","MetadataTypeName":"HP.LR.Vugen.Iteration","Id":1},{"CategoryName":"VuGen.Replay","MetadataTypeName":"HP.LR.Vugen.NotifyTransaction","Id":2},{"CategoryName":"VuGen.Replay","MetadataTypeName":"Utt.Debugger.Warning","Id":3},{"CategoryName":"VuGen.Replay","MetadataTypeName":"Utt.Debugger.Error","Id":4},{"CategoryName":"VuGen.Replay","MetadataTypeName":"HP.LR.Vugen.NotifyAny","Id":5},{"CategoryName":"VuGen.Replay","MetadataTypeName":"HP.LR.Vugen.NotifySavingParameter","Id":6},{"CategoryName":"VuGen.Replay","MetadataTypeName":"HP.LR.Vugen.NotifyParameterSubstitution","Id":7}]}